GoodCalculator/GoodCalculator_cli.py
GoodCalculator/__init__.py
GoodCalculator/calculator.py
GoodCalculator/goodOperator.py
GoodCalculator-0.0.10.dist-info/LICENSE.txt
GoodCalculator-0.0.10.dist-info/METADATA
GoodCalculator-0.0.10.dist-info/WHEEL
GoodCalculator-0.0.10.dist-info/entry_points.txt
GoodCalculator-0.0.10.dist-info/top_level.txt
GoodCalculator-0.0.10.dist-info/RECORD
