Metadata-Version: 2.1
Name: GoodCalculator
Version: 0.0.10
Summary: A calculator
Home-page: https://github.com/pypa/sampleproject
Author: Joey
Author-email: test@gmail.com
License: UNKNOWN
Platform: UNKNOWN
Classifier: Programming Language :: Python :: 3
Classifier: License :: OSI Approved :: MIT License
Classifier: Operating System :: OS Independent
Requires-Python: >=3.6
Requires-Dist: markdown
